griddb/__about__.py
griddb/__init__.py
griddb-0.0.1.dist-info/METADATA
griddb-0.0.1.dist-info/WHEEL
griddb-0.0.1.dist-info/licenses/LICENSE.txt
griddb-0.0.1.dist-info/RECORD
